{
  "generateDate": "2025-11-06T09:43:24.999Z",
  "targetDate": "2025-10-20",
  "totalCount": 7,
  "mainBoardCount": 3,
  "growthBoardCount": 0,
  "calculationMethod": "基于前日收盘价计算涨跌幅，涨幅>=9.9%为涨停",
  "stocks": [
    {
      "rank": 4,
      "code": "002196",
      "name": "方正电机",
      "exchange": "SZSE",
      "boardType": "其他",
      "prevClose": 1166,
      "last": 1283,
      "limitThreshold": 9.9,
      "limitRate": 10.034305317324185,
      "actualChangeRate": 10.034305317324185,
      "change": 117,
      "open": 1186,
      "high": 1283,
      "low": 1156,
      "volume": 1177037,
      "amount": 1423005670.78,
      "amp_rate": 450,
      "tradephase": "T111"
    },
    {
      "rank": 5,
      "code": "002255",
      "name": "海陆重工",
      "exchange": "SZSE",
      "boardType": "其他",
      "prevClose": 1188,
      "last": 1307,
      "limitThreshold": 9.9,
      "limitRate": 10.016835016835017,
      "actualChangeRate": 10.016835016835017,
      "change": 119,
      "open": 1307,
      "high": 1307,
      "low": 1307,
      "volume": 51357,
      "amount": 67123599,
      "amp_rate": 245,
      "tradephase": "T111"
    },
    {
      "rank": 2,
      "code": "000922",
      "name": "佳电股份",
      "exchange": "SZSE",
      "boardType": "深交所主板",
      "prevClose": 1338,
      "last": 1472,
      "limitThreshold": 9.9,
      "limitRate": 10.014947683109119,
      "actualChangeRate": 10.014947683109119,
      "change": 134,
      "open": 1472,
      "high": 1472,
      "low": 1472,
      "volume": 91163,
      "amount": 134192318.72,
      "amp_rate": 225,
      "tradephase": "T111"
    },
    {
      "rank": 1,
      "code": "000838",
      "name": "财信发展",
      "exchange": "SZSE",
      "boardType": "深交所主板",
      "prevClose": 320,
      "last": 352,
      "limitThreshold": 9.9,
      "limitRate": 10,
      "actualChangeRate": 10,
      "change": 32,
      "open": 319,
      "high": 352,
      "low": 310,
      "volume": 1487175,
      "amount": 499094625.27,
      "amp_rate": 944,
      "tradephase": "T111"
    },
    {
      "rank": 7,
      "code": "002384",
      "name": "东山精密",
      "exchange": "SZSE",
      "boardType": "其他",
      "prevClose": 6860,
      "last": 7546,
      "limitThreshold": 9.9,
      "limitRate": 10,
      "actualChangeRate": 10,
      "change": 686,
      "open": 6929,
      "high": 7546,
      "low": 6929,
      "volume": 1030434,
      "amount": 7608584664.28,
      "amp_rate": 649,
      "tradephase": "T111"
    },
    {
      "rank": 3,
      "code": "000993",
      "name": "闽东电力",
      "exchange": "SZSE",
      "boardType": "深交所主板",
      "prevClose": 1284,
      "last": 1412,
      "limitThreshold": 9.9,
      "limitRate": 9.968847352024921,
      "actualChangeRate": 9.968847352024921,
      "change": 128,
      "open": 1411,
      "high": 1412,
      "low": 1406,
      "volume": 262708,
      "amount": 370893574.2,
      "amp_rate": 243,
      "tradephase": "T111"
    },
    {
      "rank": 6,
      "code": "002300",
      "name": "太阳电缆",
      "exchange": "SZSE",
      "boardType": "其他",
      "prevClose": 724,
      "last": 796,
      "limitThreshold": 9.9,
      "limitRate": 9.94475138121547,
      "actualChangeRate": 9.94475138121547,
      "change": 72,
      "open": 775,
      "high": 796,
      "low": 760,
      "volume": 908917,
      "amount": 714877984.68,
      "amp_rate": 304,
      "tradephase": "T111"
    }
  ]
}